jasper/__init__.py
jasper/blast.py
jasper/crispr.py
jasper/mash.py
jasper/merge.py
jasper/trna.py
jasper/utils.py
jasper/wish.py
jasper_vh-1.1.data/scripts/jasper-vh
jasper_vh-1.1.dist-info/METADATA
jasper_vh-1.1.dist-info/RECORD
jasper_vh-1.1.dist-info/WHEEL
jasper_vh-1.1.dist-info/top_level.txt
