Metadata-Version: 2.1
Name: jasper-vh
Version: 1.1
Summary: Just a simple virus's hosts predictor
Home-page: https://github.com/777moneymaker/jasper
Author: Milosz Chodkowski
Author-email: milosz.chodkowski@student.put.poznan.pl
License: GPLv3
Download-URL: https://github.com/777moneymaker/jasper/archive/v1.0.2.tar.gz
Keywords: bioinformatics sequence DNA trna CRISPR blast virus host
Platform: UNKNOWN
Classifier: Development Status :: 4 - Beta
Classifier: Environment :: Console
Classifier: Intended Audience :: Education
Classifier: Intended Audience :: Healthcare Industry
Classifier: Intended Audience :: Information Technology
Classifier: License :: OSI Approved :: GNU General Public License v3 (GPLv3)
Classifier: Operating System :: MacOS
Classifier: Operating System :: POSIX :: Linux
Classifier: Programming Language :: Python :: 3 :: Only
Classifier: Topic :: Scientific/Engineering
Classifier: Topic :: Scientific/Engineering :: Bio-Informatics
Requires-Dist: biopython
Requires-Dist: numpy
Requires-Dist: pandas
Requires-Dist: argparse
